autofill/__init__.py
autofill/autofill.py
autofill-0.1.0.dist-info/AUTHORS.md
autofill-0.1.0.dist-info/LICENSE
autofill-0.1.0.dist-info/METADATA
autofill-0.1.0.dist-info/WHEEL
autofill-0.1.0.dist-info/top_level.txt
autofill-0.1.0.dist-info/RECORD
