Metadata-Version: 2.1
Name: autofill
Version: 0.1.0
Summary: Autofill is a Python library for dealing with auto-completion of words.
Home-page: https://github.com/vyshuks/autofill
Author: Vysakh KS
Author-email: vyshuks@gmail.com
License: MIT license
Keywords: autofill
Platform: UNKNOWN
Classifier: Development Status :: 2 - Pre-Alpha
Classifier: Intended Audience :: Developers
Classifier: License :: OSI Approved :: MIT License
Classifier: Natural Language :: English
Classifier: Programming Language :: Python :: 3
Classifier: Programming Language :: Python :: 3.6
Classifier: Programming Language :: Python :: 3.7
Classifier: Programming Language :: Python :: 3.8
Requires-Python: >=3.6
License-File: LICENSE
License-File: AUTHORS.md
